rumex/__init__.py
rumex/parsing/__init__.py
rumex/parsing/builder.py
rumex/parsing/core.py
rumex/parsing/parser.py
rumex/parsing/table.py
rumex/parsing/tokenizer.py
rumex/runner.py
rumex/utils.py
rumex-0.7.0.dist-info/LICENSE
rumex-0.7.0.dist-info/METADATA
rumex-0.7.0.dist-info/WHEEL
rumex-0.7.0.dist-info/RECORD
