Metadata-Version: 2.1
Name: rumex
Version: 0.7.0
Summary: 
Author: uigctaw
Author-email: uigctaw@metadata.social
Requires-Python: >=3.12,<4.0
Classifier: Programming Language :: Python :: 3
Classifier: Programming Language :: Python :: 3.12
